LICENSE
README.md
setup.py
hpt/__init__.py
hpt/run.py
hpt/run_eval.py
hpt/train_test.py
hpt_robot.egg-info/PKG-INFO
hpt_robot.egg-info/SOURCES.txt
hpt_robot.egg-info/dependency_links.txt
hpt_robot.egg-info/requires.txt
hpt_robot.egg-info/top_level.txt