Metadata-Version: 2.1
Name: hpt-robot
Version: 0.0.1
Summary: evaluating HPTs for robotics
Home-page: https://liruiw.github.io/hpt
Author: Lirui Wang
Author-email: liruiw@mit.edu
License: MIT
Classifier: Programming Language :: Python :: 3
Classifier: License :: OSI Approved :: MIT License
License-File: LICENSE
Requires-Dist: setuptools>=61.0
